pollination/honeybee_radiance/__init__.py
pollination/honeybee_radiance/coefficient.py
pollination/honeybee_radiance/contrib.py
pollination/honeybee_radiance/edit.py
pollination/honeybee_radiance/glare.py
pollination/honeybee_radiance/grid.py
pollination/honeybee_radiance/matrix.py
pollination/honeybee_radiance/modifier.py
pollination/honeybee_radiance/multiphase.py
pollination/honeybee_radiance/octree.py
pollination/honeybee_radiance/post_process.py
pollination/honeybee_radiance/raytrace.py
pollination/honeybee_radiance/rpict.py
pollination/honeybee_radiance/schedule.py
pollination/honeybee_radiance/sky.py
pollination/honeybee_radiance/study.py
pollination/honeybee_radiance/sun.py
pollination/honeybee_radiance/translate.py
pollination/honeybee_radiance/view.py
pollination/honeybee_radiance/viewfactor.py
pollination_honeybee_radiance-0.22.73.dist-info/LICENSE
pollination_honeybee_radiance-0.22.73.dist-info/METADATA
pollination_honeybee_radiance-0.22.73.dist-info/WHEEL
pollination_honeybee_radiance-0.22.73.dist-info/top_level.txt
pollination_honeybee_radiance-0.22.73.dist-info/RECORD
