Metadata-Version: 2.1
Name: pollination-honeybee-radiance
Version: 0.22.73
Summary: Honeybee Radiance plugin for Pollination.
Home-page: https://github.com/pollination/pollination-honeybee-radiance
Author: ladybug-tools
Author-email: info@ladybug.tools
Maintainer: mostapha, ladybug-tools
Maintainer-email: mostapha@ladybug.tools, info@ladybug.tools
License: PolyForm Shield License 1.0.0, https://polyformproject.org/wp-content/uploads/2020/06/PolyForm-Shield-1.0.0.txt
Project-URL: icon, https://raw.githubusercontent.com/ladybug-tools/artwork/master/icons_bugs/grasshopper_tabs/HB-Radiance.png
Project-URL: docker, https://hub.docker.com/r/ladybugtools/honeybee-radiance
Keywords: honeybee,radiance,ladybug-tools,daylight
License-File: LICENSE
Requires-Dist: pollination-dsl>=0.17.1
Requires-Dist: honeybee-radiance>=1.66.219
